mapfun/__init__.py
mapfun/mapfun.py
mapfun-0.0.5.dist-info/LICENCE
mapfun-0.0.5.dist-info/METADATA
mapfun-0.0.5.dist-info/WHEEL
mapfun-0.0.5.dist-info/top_level.txt
mapfun-0.0.5.dist-info/RECORD
