Metadata-Version: 2.1
Name: mapfun
Version: 0.0.5
Summary: mapfun
Author: Zakaria Elalaoui
License: UNKNOWN
Keywords: zikojs,python,map
Platform: UNKNOWN
Classifier: Development Status :: 1 - Planning
Classifier: Intended Audience :: Developers
Classifier: Programming Language :: Python :: 3
Classifier: Operating System :: Unix
Classifier: Operating System :: MacOS :: MacOS X
Classifier: Operating System :: Microsoft :: Windows
License-File: LICENCE
